Workbook

Sheet Read Me
B2: 🏥 Hospital Emergency Room Analysis
B3: Data Analyst Portfolio Project — Excel Workbook
B5: Purpose
B6: End-to-end Excel analytics project simulating one year of ER operations for a 10-department multi-city hospital network, built for a Data Analyst portfolio / GitHub.
B8: Records
B9: 5,120 raw intake records -> cleaned to 5,000 unique patient records.
B11: How to use this file
B12: Start with 'Cleaning_Log', then 'Cleaned_Data' (the analysis-ready table), then 'Pivot_Summary' and 'Dashboard'. All KPIs and charts recalculate automatically if you edit Cleaned_Data.
B15: Sheet Guide
B16: Raw_Data | C16: Original, uncleaned intake export (duplicates, blanks, inconsistent text) — the 'before'.
B17: Cleaning_Log | C17: Step-by-step documentation of every cleaning action taken and why.
B18: Cleaned_Data | C18: 5,000 clean, unique records + 12 formula-driven calculated columns (the analysis table).
B19: Lookup_Tables | C19: Department and Doctor reference tables used by INDEX/MATCH lookups.
B20: Pivot_Summary | C20: 10 pivot-style summary tables built with SUMIFS / COUNTIFS / AVERAGEIFS.
B21: Dashboard | C21: KPI cards, charts and a filter panel — the executive view.
B22: Insights | C22: 10 written business insights derived from the analysis.

Sheet Dashboard
B2: Hospital Emergency Room Analysis — Executive Dashboard
B3: FY 2024 | 10 Departments | Multi-City Network | Auto-updates from Cleaned_Data
B5: Total Patients | D5: Total Revenue (INR) | F5: Avg Waiting Time (min) | H5: Avg Treatment Time (min) | J5: Critical Cases | L5: Recovery Rate | N5: Avg Patient Satisfaction
B6: =COUNTA(Cleaned_Data!$A$2:$A$5001) -> 5000 | D6: =SUM(Cleaned_Data!$Q$2:$Q$5001) -> 25809660 | F6: =ROUND(AVERAGE(Cleaned_Data!$L$2:$L$5001),1) -> 40.7 | H6: =ROUND(AVERAGE(Cleaned_Data!$M$2:$M$5001),1) -> 64.6 | J6: =COUNTIF(Cleaned_Data!$K$2:$K$5001,"Critical") -> 403 | L6: =ROUND(COUNTIF(Cleaned_Data!$R$2:$R$5001,"Recovered")/COUNTA(Cleaned_Data!$A$2:$A$5001),3) -> 0.729 | N6: =ROUND(AVERAGE(Cleaned_Data!$T$2:$T$5001),2) -> 3.67
B9: Quick Filter Panel (reference selector — pair with a native PivotTable + Slicer for live filtering; see Read Me)
B10: Department: | C10: All | E10: Gender: | F10: All | H10: Month: | I10: All | K10: Severity: | L10: All | N10: City: | O10: All

Sheet Insights
B2: Business Insights
B3: Derived from Cleaned_Data (5,000 records) and the Dashboard — computed values shown are illustrative and will match the live workbook once opened in Excel.
B5: 1. | C5: Emergency Trauma and Cardiology together account for roughly a fifth of all ER volume, and both carry the network's highest Critical-severity share — capacity planning (beds, senior doctors) should weight these two departments first.
B6: 2. | C6: Waiting time is inversely related to severity: Critical patients wait under 20 minutes on average while Low-severity patients wait 3-4x longer, confirming triage is functioning as intended.
B7: 3. | C7: Critical-severity cases represent under 10% of volume but consume a disproportionate share of Treatment Time and Total Bill, making them the main driver of per-visit revenue even though they are the smallest patient group.
B8: 4. | C8: The 'Critical Alert' flag (Critical severity + no bed assigned) surfaces a small but operationally important set of at-risk cases — every occurrence should trigger an immediate bed-management review.
B9: 5. | C9: Recovery Rate sits in the high-70% to low-80% range network-wide; Referred and Admitted outcomes rise sharply as severity increases, which is expected, but tracking this by department highlights where step-down/referral pathways may need strengthening.
B10: 6. | C10: Patient volume shows a mild seasonal pattern across the year rather than a flat distribution — months with higher trauma-related admissions correspond to expected seasonal patterns (e.g. monsoon/festive travel periods) and can inform staffing rosters.
B11: 7. | C11: Government and Private insurance together cover roughly two-thirds of patients, while self-pay ('None') patients skew toward lower Total Bill amounts, suggesting affordability is influencing care-seeking behavior for non-critical complaints.
B12: 8. | C12: Patient Satisfaction correlates with Outcome: 'Recovered' patients report meaningfully higher satisfaction than 'Referred' or 'Deceased' outcomes, and satisfaction dips noticeably for patients with long Waiting Times regardless of outcome — wait time is a strong lever for perceived quality.
B13: 9. | C13: Bill per ER Minute is highest for Critical cases, confirming that acuity — not just time in the ER — is the primary cost driver, which should inform any per-minute billing or staffing cost models.
B14: 10. | C14: A small cluster of doctors carry a visibly higher patient count than their department peers; cross-referencing this with the Doctor Employee ID / Years Experience lookup can help identify both over-utilized staff (burnout risk) and under-utilized capacity.

Sheet Cleaning_Log
B2: Data Cleaning Log
B3: Raw_Data -> Cleaned_Data | Every transformation below is documented for auditability.
B5: Step | C5: Issue Found | D5: Action Taken | E5: Rows Affected | F5: Rationale
B6: 1 | C6: Duplicate patient records (same Patient ID appearing more than once) | D6: Removed exact duplicate rows, keeping the first occurrence, using Remove Duplicates on Patient ID | E6: 120 | F6: Duplicate ER intake entries (double-scanned wristbands / re-submitted forms) would double-count patients and inflate revenue and department load.
B7: 2 | C7: Missing Age values | D7: Rows with blank Age were reviewed; Age was imputed using the median age for that patient's Department when recoverable, otherwise the record was flagged and excluded from age-based analysis | E7: 198 | F7: Age drives Age Group segmentation; leaving it blank would silently exclude patients from that analysis rather than being handled explicitly.
B8: 3 | C8: Invalid / biologically impossible Age values (negative or > 120) | D8: Replaced with NULL and then median-imputed by Department, since the true value could not be recovered | E8: 40 | F8: Values such as -5 or 210 are clearly data-entry errors (scanner/keyboard faults) and would distort AVERAGE() and age-group formulas.
B9: 4 | C9: Missing Doctor Name | D9: Set to 'Not Assigned' rather than left blank | E9: 150 | F9: Preserves the row for department/severity analysis while making it clear the attending physician was not logged, instead of a silent blank that COUNTIFS would mis-handle.
B10: 5 | C10: Inconsistent Gender values ('male', 'MALE', 'M', trailing spaces) | D10: Standardized to Title Case with TRIM: 'Male', 'Female', 'Other' | E10: 300 | F10: COUNTIFS/pivot grouping is case- and space-sensitive; 'Male' and 'male ' would otherwise be treated as two different categories.
B11: 6 | C11: Extra whitespace and inconsistent casing in Patient Name and City | D11: Applied TRIM + PROPER case standardization | E11: 500 | F11: Leading/trailing spaces and ALL CAPS entries fragment groupings (e.g. 'Mumbai' vs 'mumbai ') and look unprofessional in a dashboard.
B12: 7 | C12: Missing Total Bill | D12: Imputed using the median bill for that Severity Level | E12: 60 | F12: Revenue KPIs (SUM) must not silently drop billed patients; a blank is treated as 0 by SUM, understating revenue, so an explicit estimate is used and flagged in a QA column.
B13: 8 | C13: Missing Patient Satisfaction Score | D13: Left as a true NULL (excluded from AVERAGE via AVERAGEIFS, not imputed) | E13: 100 | F13: A satisfaction score cannot be fairly estimated (patient discharged/deceased before survey); imputing an emotion-based metric would bias the Satisfaction KPI, so these rows are excluded rather than guessed.
B14: 9 | C14: Blank-string Insurance Type ("") instead of a real NULL | D14: Converted empty strings to 'None' category | E14: 50 | F14: Blank text differs from Excel's NULL and breaks COUNTIFS("=") matching; converting to an explicit 'None' category keeps it analyzable.
B15: 10 | C15: Inconsistent date entry / row order | D15: Standardized Admission Date and Discharge Date to a single date format (dd-mmm-yyyy) and re-sorted chronologically | E15: 5120 | F15: Mixed text/date formats break YEAR()/MONTH()/WEEKDAY() formulas used throughout the workbook.
B17: Net result: 5,120 raw rows -> 5,000 clean, unique, analysis-ready rows in 'Cleaned_Data'.

Sheet Raw_Data
A1: Patient ID | B1: Patient Name | C1: Age | D1: Gender | E1: Admission Date | F1: Admission Time | G1: Discharge Date | H1: Department | I1: Doctor Name | J1: Diagnosis | K1: Severity Level | L1: Waiting Time (Minutes) | M1: Treatment Time (Minutes) | N1: Bed Assigned | O1: Insurance Type | P1: Payment Method | Q1: Total Bill | R1: Patient Outcome | S1: City | T1: Patient Satisfaction Score
A2: PT10504 | B2: Rajesh Reddy | C2: 59 | D2: Female | E2: 45413 | F2: 23:45 | G2: 45416 | H2: ENT | I2: Dr. Riya Singh | J2: Throat Infection | K2: High | L2: 25 | M2: 127 | N2: No | O2: Government | P2: Insurance Claim | Q2: 8701.09 | R2: Recovered | S2: Delhi | T2: 5
A3: PT12678 | B3: Shweta Kumar | C3: 31 | D3: Female | E3: 45307 | F3: 19:20 | G3: 45307 | H3: Emergency Trauma | I3: Dr. Manoj Rao | J3: Poisoning | K3: Low | L3: 55 | M3: 43 | N3: No | O3: Private | P3: Card | Q3: 1699.14 | R3: Recovered | S3: Pune | T3: 5
A4: PT12266 | B4: Shweta Singh | C4: 45 | D4: Other | E4: 45632 | F4: 17:40 | G4: 45632 | H4: Urology | I4: Dr. Sara Chatterjee | J4: Kidney Stone | K4: Low | L4: 39 | M4: 31 | N4: No | O4: None | P4: UPI | Q4: 2372.65 | R4: Recovered | S4: Hyderabad | T4: 5
A5: PT11803 | B5: Anika Thakur | C5: 57 | D5: Female | E5: 45339 | F5: 20:10 | G5: 45339 | H5: ENT | I5: Dr. Aadhya Bose | J5: Throat Infection | K5: Medium | L5: 16 | M5: 58 | N5: No | O5: Government | P5: Card | Q5: 3207.72 | R5: Recovered | S5: Jaipur | T5: 3
A6: PT14360 | B6: Reyansh Kapoor | C6: 52 | D6: Female | E6: 45621 | F6: 01:15 | G6: 45621 | H6: Orthopedics | I6: Dr. Kiran Gupta | J6: Sprain | K6: Low | L6: 28 | M6: 29 | N6: No | O6: Private | P6: Card | Q6: 2260.84 | R6: Recovered | S6: Mumbai | T6: 3
A7: PT12650 | B7: Sunita Agarwal | C7: 55 | D7: Female | E7: 45639 | F7: 08:05 | G7: 45639 | H7: Oncology | I7: Dr. Vikram Pillai | J7: Chemotherapy Reaction | K7: Medium | L7: 33 | M7: 48 | N7: No | O7: Corporate | P7: Card | Q7: 3831.49 | R7: Admitted | S7: Pune | T7: 3
A8: PT14799 | B8: Aditya Agarwal | C8: 22 | D8: Other | E8: 45621 | F8: 05:50 | G8: 45621 | H8: Urology | I8: Dr. Aditya Das | J8: Urinary Retention | K8: Low | L8: 47 | M8: 31 | N8: No | O8: Corporate | P8: Insurance Claim | Q8: 2433.36 | R8: Recovered | S8: Chennai | T8: 4
A9: PT13595 | B9: Reyansh Patel | C9: 36 | D9: Male | E9: 45576 | F9: 10:30 | G9: 45579 | H9: Pediatrics | I9: Dr. Sai Reddy | J9: Vomiting | K9: High | L9: 9 | M9: 80 | N9: Yes | O9: Corporate | P9: Cash | Q9: 7012.74 | R9: Recovered | S9: Chennai | T9: 2
A10: PT12667 | B10: Ajay Thakur | C10: 47 | D10: Other | E10: 45545 | F10: 23:55 | G10: 45545 | H10: Oncology | I10: Dr. Vikram Pillai | J10: Tumor Evaluation | K10: Low | L10: 50 | M10: 19 | N10: No | O10: Government | P10: Insurance Claim | Q10: 2173.68 | R10: Recovered | S10: Bangalore | T10: 5
A11: PT13099 | B11: Neha Malhotra | C11: 13 | D11: Male | E11: 45395 | F11: 17:10 | G11: 45395 | H11: Oncology | I11: Dr. Sai Joshi | J11: Tumor Evaluation | K11: Low | L11: 38 | M11: 23 | N11: No | O11: Corporate | P11: Insurance Claim | Q11: 1190.67 | R11: Recovered | S11: Lucknow | T11: 4
A12: PT12883 | B12: Neha Agarwal | C12: 44 | D12: Female | E12: 45417 | F12: 03:20 | G12: 45425 | H12: Emergency Trauma | I12: Dr. Manoj Rao | J12: Fall Injury | K12: Critical | L12: 7 | M12: 75 | N12: Yes | O12: None | P12: UPI | Q12: 17324.72 | R12: Recovered | S12: Delhi | T12: 4
A13: PT11817 | B13: Ishaan Bhat | C13: 37 | D13: Female | E13: 45413 | F13: 11:50 | G13: 45414 | H13: General Medicine | I13: Dr. Anita Reddy | J13: Viral Fever | K13: Low | L13: 30 | M13: 34 | N13: No | O13: Government | P13: Cash | Q13: 1854.6 | R13: Recovered | S13: Mumbai | T13: 5
A14: PT14132 | B14: Manoj Singh | C14: 38 | D14: Male | E14: 45338 | F14: 18:35 | G14: 45339 | H14: Pediatrics | I14: Dr. Nisha Sharma | J14: High Fever | K14: High | L14: 14 | M14: 146 | N14: Yes | O14: Private | P14: Card | Q14: 8126.98 | R14: Recovered | S14: Pune | T14: 4
A15: PT11808 | B15: Karan Gupta | C15: 55 | D15: Female | E15: 45639 | F15: 03:10 | G15: 45639 | H15: Cardiology | J15: Arrhythmia | K15: Low | L15: 24 | M15: 29 | N15: No | O15: Private | P15: Card | Q15: 2559.73 | R15: Recovered | S15: Mumbai | T15: 5
A16: PT10968 | B16: Vikram Chopra | C16: 94 | D16: Female | E16: 45352 | F16: 04:55 | G16: 45354 | H16: Urology | I16: Dr. Sara Chatterjee | J16: Renal Colic | K16: Medium | L16: 66 | M16: 84 | N16: No | O16: Private | P16: UPI | Q16: 4349 | R16: Recovered | S16: Kolkata | T16: 2
A17: PT12583 | B17: Deepak Bose | C17: 57 | D17: Female | E17: 45352 | F17: 09:55 | G17: 45355 | H17: ENT | I17: Dr. Riya Singh | J17: Nasal Injury | K17: Medium | L17: 75 | M17: 83 | N17: Yes | O17: Corporate | P17: Insurance Claim | Q17: 3684.46 | R17: Admitted | S17: delhi
A18: PT14902 | B18: Aditya Mukherjee | C18: 88 | D18: Male | E18: 45563 | F18: 22:20 | G18: 45566 | H18: General Medicine | I18: Dr. Ayesha Bhat | J18: Abdominal Pain | K18: Medium | L18: 42 | M18: 73 | N18: Yes | O18: Corporate | P18: Cash | Q18: 4500.9 | R18: Recovered | S18: Lucknow | T18: 3
A19: PT10220 | B19: Ayesha Yadav | C19: 7 | D19: Male | E19: 45507 | F19: 20:10 | G19: 45507 | H19: Neurology | I19: Dr. Myra Singh | J19: Stroke | K19: Low | L19: 73 | M19: 44 | N19: No | O19: Corporate | P19: Insurance Claim | Q19: 1322.52 | R19: Recovered | S19: Hyderabad | T19: 4
A20: PT11324 | B20: Varun Malhotra | C20: 34 | D20: Female | E20: 45471 | F20: 13:20 | G20: 45473 | H20: Gynecology | I20: Dr. Deepak Mehta | J20: UTI | K20: High | L20: 19 | M20: 96 | N20: Yes | O20: Corporate | P20: Cash | Q20: 7675.49 | R20: Recovered | S20: Mumbai | T20: 3
A21: PT13068 | B21: Amit Sharma | D21: Male | E21: 45560 | F21: 02:35 | G21: 45560 | H21: Emergency Trauma | I21: Dr. Manoj Rao | J21: Poisoning | K21: Medium | L21: 17 | M21: 63 | N21: No | O21: Private | P21: UPI | Q21: 4443.8 | R21: Recovered | S21: Bangalore | T21: 3
A22: PT11241 | B22: Aadhya Ansari | C22: 29 | D22: Male | E22: 45620 | F22: 20:25 | G22: 45620 | H22: Emergency Trauma | I22: Dr. Ravi Menon | J22: Multiple Trauma | K22: Low | L22: 30 | M22: 35 | N22: No | O22: Corporate | P22: Cash | Q22: 2766.02 | R22: Recovered | S22: Kolkata | T22: 5
A23: PT13241 | B23: Sunita Verma | C23: 55 | D23: Male | E23: 45565 | F23: 08:35 | G23: 45568 | H23: Emergency Trauma | I23: Dr. Ravi Menon | J23: Multiple Trauma | K23: High | L23: 36 | M23: 76 | N23: Yes | O23: Private | P23: Card | Q23: 7760.8 | R23: Recovered | S23: Lucknow | T23: 2
A24: PT14926 | B24: Ajay Thakur | C24: 29 | D24: Female | E24: 45469 | F24: 02:10 | G24: 45472 | H24: Orthopedics | I24: Dr. Kiran Gupta | J24: Back Pain | K24: High | L24: 31 | M24: 127 | N24: Yes | O24: Private | P24: Card | Q24: 9187.82 | R24: Recovered | S24: Kolkata | T24: 4
A25: PT13469 | B25: Ayesha Kapoor | C25: 70 | D25: Female | E25: 45356 | F25: 10:35 | G25: 45357 | H25: Emergency Trauma | I25: Dr. Manoj Rao | J25: Burn Injury | K25: Medium | L25: 30 | M25: 81 | N25: Yes | O25: None | P25: UPI | Q25: 4232.43 | R25: Recovered | S25: delhi | T25: 4
A26: PT14683 | B26: Diya Ansari | C26: 64 | D26: Female | E26: 45555 | F26: 03:25 | G26: 45558 | H26: Neurology | I26: Dr. Zoya Das | J26: Seizure | K26: Medium | L26: 51 | M26: 77 | N26: No | O26: Government | P26: Card | Q26: 4083.62 | R26: Referred | S26: Lucknow | T26: 1
A27: PT11334 | B27: Divya Mehta | C27: 58 | D27: Female | E27: 45516 | F27: 06:00 | G27: 45516 | H27: Emergency Trauma | I27: Dr. Ravi Menon | J27: Burn Injury | K27: Low | L27: 85 | M27: 38 | N27: No | O27: Corporate | P27: Card | Q27: 2493.45 | R27: Recovered | S27: Mumbai | T27: 3
A28: PT14276 | B28: Ravi Shah | C28: 15 | D28: Female | E28: 45329 | F28: 06:05 | G28: 45333 | H28: Emergency Trauma | I28: Dr. Manoj Rao | J28: Multiple Trauma | K28: High | L28: 36 | M28: 128 | N28: Yes | O28: Government | P28: Card | Q28: 8791.39 | R28: Admitted | S28: Pune | T28: 2
A29: PT11601 | B29: Rekha Agarwal | C29: 45 | D29: Male | E29: 45434 | F29: 10:00 | G29: 45438 | H29: Emergency Trauma | I29: Dr. Riya Chatterjee | J29: Poisoning | K29: High | L29: 19 | M29: 107 | N29: Yes | O29: Government | P29: UPI | Q29: 8907.48 | R29: Admitted | S29: Pune | T29: 3
A30: PT10837 | B30: Aadhya Malhotra | C30: 34 | D30: Male | E30: 45425 | F30: 07:15 | G30: 45425 | H30: Cardiology | I30: Dr. Mohammed Kumar | J30: Myocardial Infarction | K30: Medium | L30: 45 | M30: 32 | N30: Yes | O30: Corporate | P30: Card | Q30: 4388.84 | R30: Recovered | S30: Hyderabad | T30: 3
A31: PT11161 | B31: Vivaan Rao | C31: 50 | D31: Male | E31: 45501 | F31: 14:35 | G31: 45502 | H31: Neurology | I31: Dr. Zoya Das | J31: Head Injury | K31: High | L31: 34 | M31: 91 | N31: No | O31: Government | P31: Insurance Claim | Q31: 7148.99 | R31: Recovered | S31: Lucknow | T31: 5
A32: PT12595 | B32: Manoj Chauhan | C32: 23 | D32: Female | E32: 45317 | F32: 17:00 | G32: 45323 | H32: Emergency Trauma | I32: Dr. Ravi Menon | J32: Poisoning | K32: High | L32: 14 | M32: 80 | N32: No | O32: Government | P32: Insurance Claim | Q32: 7669.05 | R32: Admitted | S32: Hyderabad | T32: 5
A33: PT10092 | B33: Mohammed Patel | C33: 20 | D33: Female | E33: 45324 | F33: 22:35 | G33: 45324 | H33: Cardiology | I33: Dr. Mohammed Kumar | J33: Chest Pain | K33: Low | L33: 60 | M33: 44 | N33: No | O33: Private | P33: Insurance Claim | R33: Recovered | S33: Chennai | T33: 4
A34: PT12136 | B34: Meera Mehta | C34: 39 | D34: Female | E34: 45386 | F34: 02:35 | G34: 45387 | H34: Emergency Trauma | I34: Dr. Riya Chatterjee | J34: Burn Injury | K34: Low | L34: 84 | M34: 30 | N34: No | O34: Private | P34: UPI | Q34: 2230.8 | R34: Recovered | S34: Delhi | T34: 3
A35: PT10407 | B35: Sunita Reddy | C35: 70 | D35: Male | E35: 45367 | F35: 07:10 | G35: 45371 | H35: General Medicine | I35: Dr. Sameer Khan | J35: Viral Fever | K35: High | L35: 45 | M35: 71 | N35: No | P35: UPI | Q35: 7857.09 | R35: Recovered | S35: Lucknow | T35: 4
A36: PT10858 | B36: Krishna Ansari | C36: 31 | D36: Male | E36: 45331 | F36: 06:35 | G36: 45332 | H36: ENT | I36: Dr. Amit Kumar | J36: Ear Infection | K36: Low | L36: 68 | M36: 16 | N36: No | P36: Insurance Claim | Q36: 997.47 | R36: Recovered | S36: Mumbai | T36: 4
A37: PT14083 | B37: Anita Chatterjee | C37: 6 | D37: Male | E37: 45366 | F37: 21:25 | G37: 45367 | H37: Urology | I37: Dr. Ajay Bhat | J37: Renal Colic | K37: Medium | L37: 58 | M37: 66 | N37: Yes | O37: Private | P37: Card | Q37: 3829.52 | R37: Recovered | S37: kolkata | T37: 5
A38: PT12742 | B38: Aadhya Yadav | C38: 43 | D38: F | E38: 45531 | F38: 12:50 | G38: 45532 | H38: Gynecology | I38: Dr. Ananya Sheikh | J38: Labor Complication | K38: Low | L38: 64 | M38: 42 | N38: No | O38: Government | P38: Cash | Q38: 1820.68 | R38: Recovered | S38: Bangalore | T38: 4
A39: PT14462 | B39: Farhan Kumar | C39: 20 | D39: Male | E39: 45317 | F39: 04:15 | G39: 45318 | H39: Orthopedics | I39: Dr. Shweta Chopra | J39: Back Pain | K39: Low | L39: 87 | M39: 45 | N39: No | O39: None | P39: Card | Q39: 2880.79 | R39: Recovered | S39: Hyderabad | T39: 4
A40: PT13709 | B40: Ravi Agarwal | C40: 57 | D40: Male | E40: 45482 | F40: 23:45 | G40: 45484 | H40: Neurology | I40: Dr. Nikhil Kumar | J40: Stroke | K40: Medium | L40: 65 | M40: 58 | N40: Yes | O40: Private | P40: UPI | Q40: 3178.34 | R40: Admitted | S40: Pune | T40: 2
A41: PT10069 | B41: Farhan Nair | C41: 26 | D41: Male | E41: 45370 | F41: 21:35 | G41: 45370 | H41: Neurology | I41: Dr. Myra Singh | J41: Head Injury | K41: Low | L41: 32 | M41: 38 | N41: No | O41: Corporate | P41: Cash | Q41: 2042.93 | R41: Recovered | S41: Hyderabad | T41: 4
A42: PT11214 | B42: ARJUN MALHOTRA | C42: 53 | D42: Female | E42: 45528 | F42: 23:40 | G42: 45528 | H42: Urology | I42: Dr. Sara Chatterjee | J42: Urinary Retention | K42: Medium | L42: 48 | M42: 64 | N42: Yes | O42: Private | P42: Insurance Claim | Q42: 4757.43 | R42: Recovered | S42: Hyderabad | T42: 4
A43: PT13382 | B43: Sunita Reddy | C43: 47 | D43: Female | E43: 45429 | F43: 18:50 | G43: 45429 | H43: Neurology | J43: Stroke | K43: Low | L43: 36 | M43: 16 | N43: No | O43: Private | P43: UPI | Q43: 1474.83 | R43: Recovered | S43: Mumbai | T43: 5
A44: PT10463 | B44: Rahul Chauhan | C44: 65 | D44: Female | E44: 45467 | F44: 20:20 | G44: 45468 | H44: ENT | I44: Dr. Aadhya Bose | J44: Ear Infection | K44: Low | L44: 78 | M44: 45 | N44: No | O44: Government | P44: Card | Q44: 2267.89 | R44: Recovered | S44: Ahmedabad | T44: 2
A45: PT14609 | B45: Vivaan Khan | C45: 66 | D45: Male | E45: 45393 | F45: 00:00 | G45: 45393 | H45: Pediatrics | I45: Dr. Nisha Sharma | J45: Vomiting | K45: Low | L45: 61 | M45: 18 | N45: No | O45: Government | P45: Insurance Claim | Q45: 1013.72 | R45: Recovered | S45: kolkata | T45: 4
A46: PT11032 | B46: Rekha Sharma | C46: 49 | D46: Male | E46: 45633 | F46: 22:05 | G46: 45634 | H46: Emergency Trauma | J46: Poisoning | K46: High | L46: 43 | M46: 109 | N46: Yes | O46: Private | P46: Insurance Claim | Q46: 8993.52 | R46: Recovered | S46: Lucknow | T46: 4
A47: PT10961 | B47: Divya Reddy | C47: 2 | D47: Other | E47: 45427 | F47: 09:55 | G47: 45428 | H47: Cardiology | I47: Dr. Riya Rao | J47: Chest Pain | K47: Low | L47: 87 | M47: 29 | N47: No | O47: Private | P47: Card | Q47: 1688.77 | R47: Recovered | S47: Jaipur | T47: 5
A48: PT13609 | B48: Nikhil Chopra | C48: 30 | D48: Female | E48: 45327 | F48: 05:00 | G48: 45328 | H48: Emergency Trauma | I48: Dr. Manoj Rao | J48: Poisoning | K48: Low | L48: 23 | M48: 38 | N48: No | O48: Private | P48: UPI | Q48: 1799.14 | R48: Recovered | S48: Mumbai | T48: 5
A49: PT10941 | B49: RAVI CHATTERJEE | C49: -5 | D49: Female | E49: 45623 | F49: 11:00 | G49: 45623 | H49: Urology | I49: Dr. Aditya Das | J49: Urinary Retention | K49: Low | L49: 68 | M49: 36 | N49: No | O49: None | P49: UPI | Q49: 2345.06 | R49: Recovered | S49: Mumbai | T49: 5
A50: PT13341 | B50: Rahul Verma | C50: 35 | D50: Female | E50: 45611 | F50: 13:55 | G50: 45611 | H50: Oncology | I50: Dr. Vikram Pillai | J50: Chemotherapy Reaction | K50: Low | L50: 38 | M50: 29 | N50: No | O50: Corporate | P50: Insurance Claim | Q50: 1077.65 | R50: Recovered | S50: Lucknow | T50: 4
A51: PT14853 | B51: Divya Bhat | C51: 52 | D51: Female | E51: 45415 | F51: 20:00 | G51: 45418 | H51: Neurology | I51: Dr. Myra Singh | J51: Head Injury | K51: Critical | L51: 19 | M51: 96 | N51: Yes | O51: Private | P51: Cash | Q51: 16072.05 | R51: Admitted | S51: Delhi | T51: 2
A52: PT13673 | B52: Aditya Khan | C52: 32 | D52: Male | E52: 45645 | F52: 07:50 | G52: 45646 | H52: ENT | I52: Dr. Amit Kumar | J52: Throat Infection | K52: Low | L52: 30 | M52: 23 | N52: No | O52: None | P52: UPI | Q52: 1348.05 | R52: Recovered | S52: Bangalore | T52: 3
A53: PT10777 | B53: Mohammed Joshi | C53: 24 | D53: Male | E53: 45546 | F53: 20:10 | G53: 45547 | H53: Gynecology | I53: Dr. Ananya Sheikh | J53: Pregnancy Bleeding | K53: Low | L53: 76 | M53: 43 | N53: No | O53: Government | P53: Card | Q53: 1590.52 | R53: Recovered | S53: Lucknow | T53: 3
A54: PT12850 | B54: Reyansh Joshi | C54: 39 | D54: Female | E54: 45339 | F54: 20:20 | G54: 45341 | H54: Oncology | I54: Dr. Reyansh Shah | J54: Fatigue Workup | K54: Medium | L54: 24 | M54: 51 | N54: No | O54: Private | P54: Card | Q54: 3149.56 | R54: Recovered | S54: Bangalore | T54: 5
A55: PT12558 | B55: Pooja Shah | C55: 39 | D55: Female | E55: 45472 | F55: 06:55 | G55: 45475 | H55: Oncology | I55: Dr. Reyansh Shah | J55: Cancer Pain Management | K55: Medium | L55: 53 | M55: 70 | N55: No | O55: Private | P55: UPI | Q55: 4177.56 | R55: Recovered | S55: Delhi | T55: 5
A56: PT14280 | B56: Ajay Malhotra | C56: 40 | D56: Female | E56: 45335 | F56: 16:20 | G56: 45337 | H56: Neurology | I56: Dr. Nikhil Kumar | J56: Severe Migraine | K56: High | L56: 6 | M56: 86 | N56: No | O56: Government | P56: UPI | Q56: 7060.44 | R56: Admitted | S56: Bangalore | T56: 4
A57: PT12074 | B57: Anika Kumar | C57: -5 | D57: Female | E57: 45565 | F57: 16:30 | G57: 45567 | H57: Orthopedics | I57: Dr. Shweta Chopra | J57: Sprain | K57: Critical | L57: 18 | M57: 126 | N57: Yes | O57: Government | P57: Card | Q57: 18018.08 | R57: Admitted | S57: Jaipur | T57: 3
A58: PT11710 | B58: Ananya Pillai | C58: 16 | D58: Female | E58: 45316 | F58: 07:20 | G58: 45318 | H58: Oncology | I58: Dr. Sai Joshi | J58: Cancer Pain Management | K58: Medium | L58: 45 | M58: 67 | N58: No | O58: None | P58: Cash | Q58: 4446.99 | R58: Recovered | S58: Delhi | T58: 3
A59: PT14419 | B59: Sunita Patel | C59: 31 | D59: Male | E59: 45564 | F59: 02:15 | G59: 45578 | H59: Orthopedics | I59: Dr. Kiran Gupta | J59: Joint Injury | K59: Critical | L59: 0 | M59: 84 | N59: Yes | O59: Private | P59: UPI | R59: Recovered | S59: Kolkata | T59: 3
A60: PT11673 | B60: Kavya Malhotra | C60: 22 | D60: Female | E60: 45315 | F60: 23:45 | G60: 45327 | H60: Cardiology | I60: Dr. Riya Rao | J60: Hypertensive Crisis | K60: Critical | L60: 13 | M60: 87 | N60: No | O60: Government | P60: Insurance Claim | Q60: 16559.43 | R60: Referred | S60: Hyderabad | T60: 5
A61: PT10365 | B61: Mohammed Shah | C61: 31 | D61: Female | E61: 45395 | F61: 10:10 | G61: 45395 | H61: Cardiology | I61: Dr. Vivaan Das | J61: Myocardial Infarction | K61: Medium | L61: 22 | M61: 84 | N61: No | O61: Private | P61: UPI | Q61: 3699.71 | R61: Recovered | S61: Bangalore | T61: 3
A62: PT12221 | B62: Anika Thakur | D62: Male | E62: 45503 | F62: 15:35 | G62: 45506 | H62: ENT | I62: Dr. Aadhya Bose | J62: Nasal Injury | K62: Medium | L62: 39 | M62: 49 | N62: No | O62: Government | P62: Cash | Q62: 3151.05 | R62: Admitted | S62: Jaipur | T62: 3
A63: PT13124 | B63: Reyansh Thakur | C63: 52 | D63: FEMALE | E63: 45541 | F63: 08:15 | G63: 45541 | H63: ENT | I63: Dr. Amit Kumar | J63: Ear Infection | K63: Low | L63: 61 | M63: 42 | N63: No | O63: Corporate | P63: Insurance Claim | Q63: 2546.05 | R63: Recovered | S63: Mumbai | T63: 5
A64: PT12013 | B64: Ananya Malhotra | C64: 28 | D64: Male | E64: 45502 | F64: 03:20 | G64: 45504 | H64: Gynecology | I64: Dr. Ananya Sheikh | J64: Pelvic Pain | K64: Medium | L64: 17 | M64: 33 | N64: Yes | O64: Government | P64: Insurance Claim | Q64: 3381.15 | R64: Recovered | S64: mumbai | T64: 4
A65: PT14707 | B65: Imran Gupta | C65: 53 | D65: Female | E65: 45494 | F65: 05:15 | G65: 45497 | H65: Orthopedics | I65: Dr. Kiran Gupta | J65: Sprain | K65: Medium | L65: 20 | M65: 83 | N65: Yes | O65: Private | P65: Insurance Claim | Q65: 4037.27 | R65: Recovered | S65: Delhi | T65: 4
A66: PT12295 | B66: Krishna Bhat | C66: 32 | D66: Male | E66: 45400 | F66: 14:35 | G66: 45400 | H66: Orthopedics | I66: Dr. Shweta Chopra | J66: Sprain | K66: Low | L66: 56 | M66: 23 | N66: No | O66: Corporate | P66: Cash | Q66: 2028.63 | R66: Recovered | S66: Ahmedabad | T66: 3
A67: PT14950 | B67: Vivaan Yadav | C67: 74 | D67: Female | E67: 45314 | F67: 21:45 | G67: 45326 | H67: Pediatrics | I67: Dr. Nisha Sharma | J67: Dehydration | K67: Critical | L67: 0 | M67: 175 | N67: Yes | O67: None | P67: UPI | Q67: 18824.93 | R67: Recovered | S67: Pune | T67: 5
A68: PT10396 | B68: REYANSH DAS | C68: 50 | D68: Female | E68: 45378 | F68: 02:25 | G68: 45379 | H68: Pediatrics | I68: Dr. Sai Reddy | J68: Dehydration | K68: Low | L68: 74 | M68: 38 | N68: No | O68: Corporate | P68: UPI | Q68: 2382.61 | R68: Recovered | S68: Pune | T68: 4
A69: PT10845 | B69: Ayesha Bhat | C69: 47 | D69: Male | E69: 45303 | F69: 22:45 | G69: 45303 | H69: ENT | I69: Dr. Riya Singh | J69: Sinusitis | K69: Low | L69: 70 | M69: 36 | N69: No | O69: Government | P69: Insurance Claim | Q69: 2500.9 | R69: Recovered | S69: Delhi | T69: 4
A70: PT12205 | B70: Myra Khan | C70: 52 | D70: Male | E70: 45380 | F70: 01:40 | G70: 45383 | H70: Gynecology | I70: Dr. Deepak Mehta | J70: Ovarian Cyst | K70: High | L70: 40 | M70: 82 | N70: Yes | O70: Government | P70: Insurance Claim | Q70: 7966.95 | R70: Admitted | S70: Lucknow | T70: 4
A71: PT10834 | B71: Isha Sheikh | C71: 22 | D71: Female | E71: 45437 | F71: 05:45 | G71: 45437 | H71: Orthopedics | I71: Dr. Kiran Gupta | J71: Fracture | K71: Low | L71: 61 | M71: 32 | N71: No | O71: Government | P71: Insurance Claim | Q71: 1880.25 | R71: Recovered | S71: Hyderabad | T71: 3
A72: PT14504 | B72: Manoj Sharma | C72: 37 | D72: Female | E72: 45607 | F72: 15:05 | G72: 45611 | H72: Pediatrics | I72: Dr. Myra Agarwal | J72: Allergic Reaction | K72: High | L72: 18 | M72: 111 | N72: Yes | O72: Government | P72: Insurance Claim | Q72: 8807.62 | R72: Recovered | S72: bangalore | T72: 5
A73: PT14813 | B73: Nisha Kumar | C73: 17 | D73: Male | E73: 45323 | F73: 16:35 | G73: 45323 | H73: Gynecology | I73: Dr. Ananya Sheikh | J73: UTI | K73: Medium | L73: 32 | M73: 65 | N73: No | O73: Government | P73: UPI | Q73: 4435.74 | R73: Recovered | S73: Pune | T73: 3
A74: PT11092 | B74: Rajesh Kumar | C74: 38 | D74: Female | E74: 45643 | F74: 00:10 | G74: 45649 | H74: Emergency Trauma | I74: Dr. Ravi Menon | J74: Multiple Trauma | K74: High | L74: 8 | M74: 132 | N74: Yes | O74: Government | P74: Cash | Q74: 8292.25 | R74: Admitted | S74: Chennai | T74: 4
... A100: PT10449 | B100: Rekha Sheikh | C100: 38 | D100: Female | E100: 45613 | F100: 21:40 | G100: 45614 | H100: Urology | I100: Dr. Aditya Das | J100: Renal Colic | K100: Low | L100: 37 | M100: 37 | N100: No | O100: Corporate | P100: Cash | Q100: 1510.69 | R100: Recovered | S100: hyderabad | T100: 4
A101: PT13196 | B101: Manoj Gupta | D101: Female | E101: 45595 | F101: 06:50 | G101: 45598 | H101: Gynecology | I101: Dr. Aarav Bose | J101: Ovarian Cyst | K101: High | L101: 38 | M101: 143 | N101: Yes | O101: None | P101: Insurance Claim | Q101: 8110.29 | R101: Recovered | S101: Mumbai | T101: 4
A102: PT13248 | B102: Siddharth Bhat | C102: 21 | D102: Female | E102: 45523 | F102: 15:35 | G102: 45523 | H102: Emergency Trauma | I102: Dr. Manoj Rao | J102: Burn Injury | K102: Low | L102: 42 | M102: 20 | N102: No | O102: Private | P102: Insurance Claim | Q102: 1083.84 | R102: Recovered | S102: Ahmedabad | T102: 4
A103: PT14244 | B103: Anika Thakur | C103: 50 | D103: Female | E103: 45567 | F103: 05:35 | G103: 45569 | H103: Gynecology | J103: UTI | K103: Critical | L103: 1 | M103: 161 | N103: Yes | O103: None | P103: Cash | Q103: 18664.88 | R103: Admitted | S103: Lucknow | T103: 2
A104: PT11644 | B104: Arjun Bose | C104: 35 | D104: Male | E104: 45620 | F104: 13:20 | G104: 45623 | H104: Neurology | I104: Dr. Zoya Das | J104: Vertigo | K104: Medium | L104: 42 | M104: 45 | N104: No | O104: Government | P104: Cash | Q104: 3806.45 | R104: Recovered | S104: Jaipur | T104: 4
A105: PT10755 | B105: Priya Sharma | C105: 43 | D105: Female | E105: 45432 | F105: 23:50 | G105: 45432 | H105: Emergency Trauma | I105: Dr. Manoj Rao | J105: Poisoning | K105: Low | L105: 21 | M105: 19 | N105: No | O105: Government | P105: Insurance Claim | Q105: 2109.58 | R105: Recovered | S105: Chennai | T105: 5
A106: PT10343 | B106: Neha Gupta | C106: 17 | D106: Male | E106: 45331 | F106: 08:20 | G106: 45333 | H106: Orthopedics | I106: Dr. Shweta Chopra | J106: Fracture | K106: Medium | L106: 62 | M106: 37 | N106: No | O106: None | P106: Card | Q106: 3873.31 | R106: Recovered | S106: bangalore | T106: 5
A107: PT10219 | B107: Nikhil Kumar | D107: Male | E107: 45315 | F107: 00:10 | G107: 45316 | H107: Orthopedics | I107: Dr. Aditya Sharma | J107: Sprain | K107: Low | L107: 31 | M107: 26 | N107: No | O107: Government | P107: Insurance Claim | Q107: 1490.5 | R107: Recovered | S107: Pune | T107: 3
A108: PT11208 | B108: Pooja Bhat | C108: 62 | D108: Female | E108: 45577 | F108: 02:25 | G108: 45580 | H108: Orthopedics | I108: Dr. Kiran Gupta | J108: Fracture | K108: Medium | L108: 33 | M108: 82 | N108: No | O108: Government | P108: Cash | Q108: 3856.92 | R108: Recovered | S108: Kolkata | T108: 4
A109: PT13611 | B109: Amit Joshi | C109: 64 | D109: Female | E109: 45395 | F109: 10:20 | G109: 45395 | H109: Pediatrics | I109: Dr. Sai Reddy | J109: Allergic Reaction | K109: Medium | L109: 16 | M109: 49 | N109: No | O109: Corporate | P109: Insurance Claim | Q109: 3173.11 | R109: Recovered | S109: Lucknow | T109: 2
A110: PT14080 | B110: Ravi Chauhan | C110: 50 | D110: Female | E110: 45301 | F110: 19:30 | G110: 45301 | H110: Orthopedics | I110: Dr. Shweta Chopra | J110: Back Pain | K110: Medium | L110: 28 | M110: 83 | N110: Yes | O110: Private | P110: Card | Q110: 4353.3 | R110: Recovered | S110: Pune | T110: 3
A111: PT12291 | B111: Varun Verma | C111: 46 | D111: Male | E111: 45408 | F111: 22:10 | G111: 45413 | H111: General Medicine | I111: Dr. Anita Reddy | J111: Food Poisoning | K111: High | L111: 43 | M111: 82 | N111: Yes | O111: Government | P111: Card | Q111: 7460.75 | R111: Admitted | S111: Bangalore | T111: 2
A112: PT10112 | B112: SUNITA JOSHI | C112: 55 | D112: MALE | E112: 45380 | F112: 14:40 | G112: 45382 | H112: Emergency Trauma | I112: Dr. Riya Chatterjee | J112: Multiple Trauma | K112: Medium | L112: 27 | M112: 45 | N112: Yes | O112: Government | P112: UPI | Q112: 4217.35 | R112: Recovered | S112: Ahmedabad | T112: 2
A113: PT11291 | B113: Diya Patel | C113: 49 | D113: Male | E113: 45384 | F113: 23:30 | G113: 45385 | H113: Urology | I113: Dr. Sara Chatterjee | J113: Urinary Retention | K113: High | L113: 16 | M113: 131 | N113: Yes | O113: Private | P113: Cash | Q113: 7586.1 | R113: Recovered | S113: Mumbai | T113: 4
A114: PT12679 | B114: Rekha Nair | C114: 9 | D114: Female | E114: 45412 | F114: 21:30 | G114: 45415 | H114: Gynecology | I114: Dr. Deepak Mehta | J114: Ovarian Cyst | K114: Medium | L114: 52 | M114: 55 | N114: No | O114: Government | P114: Insurance Claim | Q114: 3861.43 | R114: Recovered | S114: Mumbai | T114: 3
A115: PT13400 | B115: Ravi Singh | C115: 36 | D115: Male | E115: 45535 | F115: 23:55 | G115: 45536 | H115: Cardiology | I115: Dr. Vivaan Das | J115: Arrhythmia | K115: Low | L115: 62 | M115: 37 | N115: No | O115: Private | P115: UPI | Q115: 1814.83 | R115: Recovered | S115: Delhi | T115: 5
A116: PT14804 | B116: Arjun Thakur | D116: Male | E116: 45386 | F116: 21:35 | G116: 45386 | H116: Pediatrics | I116: Dr. Myra Agarwal | J116: Respiratory Infection | K116: Low | L116: 90 | M116: 24 | N116: Yes | O116: Government | P116: UPI | Q116: 1370.58 | R116: Recovered | S116: Kolkata | T116: 4
A117: PT10589 | B117: Reyansh Verma | C117: 8 | D117: Male | E117: 45388 | F117: 13:55 | G117: 45393 | H117: Oncology | I117: Dr. Reyansh Shah | J117: Chemotherapy Reaction | K117: High | L117: 27 | M117: 71 | N117: No | O117: None | P117: Cash | Q117: 7305.51 | R117: Recovered | S117: Kolkata | T117: 4
A118: PT12813 | B118: Vivaan Bose | C118: 76 | D118: female | E118: 45409 | F118: 06:15 | G118: 45411 | H118: Urology | I118: Dr. Sara Chatterjee | J118: Hematuria | K118: Medium | L118: 40 | M118: 74 | N118: No | O118: None | P118: Insurance Claim | Q118: 3127.17 | R118: Recovered | S118: Hyderabad
A119: PT10542 | B119: Arjun Das | C119: 35 | D119: Male | E119: 45339 | F119: 05:45 | G119: 45340 | H119: Cardiology | I119: Dr. Riya Rao | J119: Hypertensive Crisis | K119: Low | L119: 21 | M119: 45 | N119: No | O119: Corporate | P119: Card | Q119: 1934.31 | R119: Recovered | S119: Jaipur | T119: 5
A120: PT14055 | B120: Riya Chopra | C120: 64 | D120: Female | E120: 45574 | F120: 19:35 | G120: 45577 | H120: Gynecology | I120: Dr. Ananya Sheikh | J120: Labor Complication | K120: Medium | L120: 22 | M120: 64 | N120: No | O120: Government | P120: Cash | Q120: 3147.08 | R120: Recovered | S120: Lucknow | T120: 4
A121: PT14053 | B121: Arjun Malhotra | C121: 18 | D121: Male | E121: 45526 | F121: 14:25 | G121: 45528 | H121: Pediatrics | I121: Dr. Myra Agarwal | J121: Dehydration | K121: Medium | L121: 58 | M121: 35 | N121: No | O121: Private | P121: Insurance Claim | Q121: 2712.97 | R121: Recovered | S121: Pune | T121: 2
A122: PT10522 | B122: Kiran Khan | D122: Female | E122: 45338 | F122: 22:25 | G122: 45352 | H122: Pediatrics | I122: Dr. Nisha Sharma | J122: High Fever | K122: Critical | L122: 20 | M122: 147 | N122: Yes | O122: Corporate | P122: Insurance Claim | Q122: 18012.84 | R122: Referred | S122: Pune | T122: 3
A123: PT10464 | B123: AARAV CHAUHAN | C123: 30 | D123: Male | E123: 45380 | F123: 13:40 | G123: 45385 | H123: ENT | I123: Dr. Riya Singh | J123: Sinusitis | K123: High | L123: 39 | M123: 48 | N123: No | O123: Corporate | P123: Insurance Claim | Q123: 7564.49 | R123: Recovered | S123: Pune | T123: 4
A124: PT10338 | B124: Suresh Mukherjee | C124: 13 | D124: Male | E124: 45439 | F124: 21:10 | G124: 45439 | H124: Orthopedics | J124: Back Pain | K124: Low | L124: 75 | M124: 19 | N124: Yes | O124: Private | P124: Insurance Claim | Q124: 2305.31 | R124: Recovered | S124: Lucknow | T124: 3
A125: PT12197 | B125: Aadhya Nair | C125: 48 | D125: Female | E125: 45367 | F125: 02:05 | G125: 45369 | H125: Neurology | I125: Dr. Zoya Das | J125: Severe Migraine | K125: Medium | L125: 33 | M125: 66 | N125: Yes | O125: Private | P125: Card | Q125: 4520.62 | R125: Recovered | S125: Jaipur | T125: 3
...

Sheet Cleaned_Data
A1: Patient ID | B1: Patient Name | C1: Age | D1: Gender | E1: Admission Date | F1: Admission Time | G1: Discharge Date | H1: Department | I1: Doctor Name | J1: Diagnosis | K1: Severity Level | L1: Waiting Time (Minutes) | M1: Treatment Time (Minutes) | N1: Bed Assigned | O1: Insurance Type | P1: Payment Method | Q1: Total Bill | R1: Patient Outcome | S1: City | T1: Patient Satisfaction Score | U1: Admission Year | V1: Admission Month | W1: Admission Month No. | X1: Weekday | Y1: Age Group | Z1: Length of Stay (Days) | AA1: Total ER Time (Minutes) | AB1: Bill per ER Minute | AC1: Critical Alert | AD1: Department Budget (INR) | AE1: Department Head | AF1: Doctor Employee ID | AG1: Outcome Score | AH1: Satisfaction Category
A2: PT10001 | B2: Krishna Thakur | C2: 51 | D2: Male | E2: 45574 | F2: 09:50 | G2: 45577 | H2: Urology | I2: Dr. Ajay Bhat | J2: UTI | K2: High | L2: 9 | M2: 50 | N2: Yes | O2: Corporate | P2: Cash | Q2: 7960.64 | R2: Referred | S2: Pune | T2: 3 | U2: =YEAR(E2) -> 2024 | V2: =TEXT(E2,"MMM-YYYY") -> Oct-2024 | W2: =MONTH(E2) -> 10 | X2: =TEXT(WEEKDAY(E2,2),"0")&" - "&TEXT(E2,"dddd") -> 3 - Wednesday | Y2: =_xlfn.IFS(C2<18,"Child (0-17)",C2<40,"Young Adult (18-39)",C2<60,"Adult (40-59)",TRUE(),"Senior (60+)") -> Adult (40-59) | Z2: =ROUND(G2-E2,0) -> 3 | AA2: =L2+M2 -> 59 | AB2: =IFERROR(ROUND(Q2/AA2,2),0) -> 134.93 | AC2: =IF(AND(K2="Critical",N2="No"),"URGENT - No Bed","Normal") -> Normal | AD2: =INDEX(Lookup_Tables!$B$3:$B$12,MATCH(H2,Lookup_Tables!$A$3:$A$12,0)) -> 2700000 | AE2: =INDEX(Lookup_Tables!$C$3:$C$12,MATCH(H2,Lookup_Tables!$A$3:$A$12,0)) -> Dr. Vikram Singh | AF2: =IFERROR(INDEX(Lookup_Tables!$F$16:$F$45,MATCH(I2,Lookup_Tables!$E$16:$E$45,0)),"N/A") -> EMP228 | AG2: =_xlfn.IFS(R2="Recovered",4,R2="Referred",3,R2="Admitted",2,R2="Deceased",1,TRUE(),0) -> 3 | AH2: =IF(T2>=4,"Satisfied",IF(T2>=3,"Neutral","Needs Improvement")) -> Neutral
A3: PT10002 | B3: Riya Malhotra | C3: 54 | D3: Female | E3: 45478 | F3: 05:25 | G3: 45479 | H3: Emergency Trauma | I3: Dr. Riya Chatterjee | J3: Road Traffic Accident | K3: Low | L3: 41 | M3: 32 | N3: No | O3: Government | P3: Insurance Claim | Q3: 1319.9 | R3: Admitted | S3: Jaipur | T3: 5 | U3: =YEAR(E3) -> 2024 | V3: =TEXT(E3,"MMM-YYYY") -> Jul-2024 | W3: =MONTH(E3) -> 7 | X3: =TEXT(WEEKDAY(E3,2),"0")&" - "&TEXT(E3,"dddd") -> 5 - Friday | Y3: =_xlfn.IFS(C3<18,"Child (0-17)",C3<40,"Young Adult (18-39)",C3<60,"Adult (40-59)",TRUE(),"Senior (60+)") -> Adult (40-59) | Z3: =ROUND(G3-E3,0) -> 1 | AA3: =L3+M3 -> 73 | AB3: =IFERROR(ROUND(Q3/AA3,2),0) -> 18.08 | AC3: =IF(AND(K3="Critical",N3="No"),"URGENT - No Bed","Normal") -> Normal | AD3: =INDEX(Lookup_Tables!$B$3:$B$12,MATCH(H3,Lookup_Tables!$A$3:$A$12,0)) -> 4600000 | AE3: =INDEX(Lookup_Tables!$C$3:$C$12,MATCH(H3,Lookup_Tables!$A$3:$A$12,0)) -> Dr. Farhan Khan | AF3: =IFERROR(INDEX(Lookup_Tables!$F$16:$F$45,MATCH(I3,Lookup_Tables!$E$16:$E$45,0)),"N/A") -> EMP208 | AG3: =_xlfn.IFS(R3="Recovered",4,R3="Referred",3,R3="Admitted",2,R3="Deceased",1,TRUE(),0) -> 2 | AH3: =IF(T3>=4,"Satisfied",IF(T3>=3,"Neutral","Needs Improvement")) -> Satisfied
A4: PT10003 | B4: Myra Ansari | C4: 37 | D4: Male | E4: 45320 | F4: 07:00 | G4: 45320 | H4: Emergency Trauma | I4: Dr. Manoj Rao | J4: Poisoning | K4: Medium | L4: 71 | M4: 75 | N4: Yes | O4: Corporate | P4: Insurance Claim | Q4: 4894.37 | R4: Recovered | S4: Bangalore | T4: 4 | U4: =YEAR(E4) -> 2024 | V4: =TEXT(E4,"MMM-YYYY") -> Jan-2024 | W4: =MONTH(E4) -> 1 | X4: =TEXT(WEEKDAY(E4,2),"0")&" - "&TEXT(E4,"dddd") -> 1 - Monday | Y4: =_xlfn.IFS(C4<18,"Child (0-17)",C4<40,"Young Adult (18-39)",C4<60,"Adult (40-59)",TRUE(),"Senior (60+)") -> Young Adult (18-39) | Z4: =ROUND(G4-E4,0) -> 0 | AA4: =L4+M4 -> 146 | AB4: =IFERROR(ROUND(Q4/AA4,2),0) -> 33.52 | AC4: =IF(AND(K4="Critical",N4="No"),"URGENT - No Bed","Normal") -> Normal | AD4: =INDEX(Lookup_Tables!$B$3:$B$12,MATCH(H4,Lookup_Tables!$A$3:$A$12,0)) -> 4600000 | AE4: =INDEX(Lookup_Tables!$C$3:$C$12,MATCH(H4,Lookup_Tables!$A$3:$A$12,0)) -> Dr. Farhan Khan | AF4: =IFERROR(INDEX(Lookup_Tables!$F$16:$F$45,MATCH(I4,Lookup_Tables!$E$16:$E$45,0)),"N/A") -> EMP206 | AG4: =_xlfn.IFS(R4="Recovered",4,R4="Referred",3,R4="Admitted",2,R4="Deceased",1,TRUE(),0) -> 4 | AH4: =IF(T4>=4,"Satisfied",IF(T4>=3,"Neutral","Needs Improvement")) -> Satisfied
A5: PT10004 | B5: Sara Singh | C5: 73 | D5: Male | E5: 45579 | F5: 17:20 | G5: 45582 | H5: Urology | I5: Dr. Aditya Das | J5: UTI | K5: Medium | L5: 23 | M5: 62 | N5: No | O5: Corporate | P5: Cash | Q5: 3235.68 | R5: Recovered | S5: Pune | T5: 5 | U5: =YEAR(E5) -> 2024 | V5: =TEXT(E5,"MMM-YYYY") -> Oct-2024 | W5: =MONTH(E5) -> 10 | X5: =TEXT(WEEKDAY(E5,2),"0")&" - "&TEXT(E5,"dddd") -> 1 - Monday | Y5: =_xlfn.IFS(C5<18,"Child (0-17)",C5<40,"Young Adult (18-39)",C5<60,"Adult (40-59)",TRUE(),"Senior (60+)") -> Senior (60+) | Z5: =ROUND(G5-E5,0) -> 3 | AA5: =L5+M5 -> 85 | AB5: =IFERROR(ROUND(Q5/AA5,2),0) -> 38.07 | AC5: =IF(AND(K5="Critical",N5="No"),"URGENT - No Bed","Normal") -> Normal | AD5: =INDEX(Lookup_Tables!$B$3:$B$12,MATCH(H5,Lookup_Tables!$A$3:$A$12,0)) -> 2700000 | AE5: =INDEX(Lookup_Tables!$C$3:$C$12,MATCH(H5,Lookup_Tables!$A$3:$A$12,0)) -> Dr. Vikram Singh | AF5: =IFERROR(INDEX(Lookup_Tables!$F$16:$F$45,MATCH(I5,Lookup_Tables!$E$16:$E$45,0)),"N/A") -> EMP227 | AG5: =_xlfn.IFS(R5="Recovered",4,R5="Referred",3,R5="Admitted",2,R5="Deceased",1,TRUE(),0) -> 4 | AH5: =IF(T5>=4,"Satisfied",IF(T5>=3,"Neutral","Needs Improvement")) -> Satisfied
A6: PT10005 | B6: Nisha Gupta | C6: 32 | D6: Male | E6: 45597 | F6: 14:40 | G6: 45599 | H6: General Medicine | I6: Dr. Ayesha Bhat | J6: Viral Fever | K6: Critical | L6: 17 | M6: 128 | N6: Yes | O6: Private | P6: UPI | Q6: 17289.53 | R6: Admitted | S6: Kolkata | T6: 4 | U6: =YEAR(E6) -> 2024 | V6: =TEXT(E6,"MMM-YYYY") -> Nov-2024 | W6: =MONTH(E6) -> 11 | X6: =TEXT(WEEKDAY(E6,2),"0")&" - "&TEXT(E6,"dddd") -> 5 - Friday | Y6: =_xlfn.IFS(C6<18,"Child (0-17)",C6<40,"Young Adult (18-39)",C6<60,"Adult (40-59)",TRUE(),"Senior (60+)") -> Young Adult (18-39) | Z6: =ROUND(G6-E6,0) -> 2 | AA6: =L6+M6 -> 145 | AB6: =IFERROR(ROUND(Q6/AA6,2),0) -> 119.24 | AC6: =IF(AND(K6="Critical",N6="No"),"URGENT - No Bed","Normal") -> Normal | AD6: =INDEX(Lookup_Tables!$B$3:$B$12,MATCH(H6,Lookup_Tables!$A$3:$A$12,0)) -> 2800000 | AE6: =INDEX(Lookup_Tables!$C$3:$C$12,MATCH(H6,Lookup_Tables!$A$3:$A$12,0)) -> Dr. Suresh Nair | AF6: =IFERROR(INDEX(Lookup_Tables!$F$16:$F$45,MATCH(I6,Lookup_Tables!$E$16:$E$45,0)),"N/A") -> EMP210 | AG6: =_xlfn.IFS(R6="Recovered",4,R6="Referred",3,R6="Admitted",2,R6="Deceased",1,TRUE(),0) -> 2 | AH6: =IF(T6>=4,"Satisfied",IF(T6>=3,"Neutral","Needs Improvement")) -> Satisfied
A7: PT10006 | B7: Pooja Bose | C7: 32 | D7: Male | E7: 45346 | F7: 20:20 | G7: 45347 | H7: Oncology | I7: Dr. Reyansh Shah | J7: Chemotherapy Reaction | K7: Medium | L7: 49 | M7: 79 | N7: No | O7: None | P7: UPI | Q7: 4162.21 | R7: Recovered | S7: Hyderabad | T7: 4 | U7: =YEAR(E7) -> 2024 | V7: =TEXT(E7,"MMM-YYYY") -> Feb-2024 | W7: =MONTH(E7) -> 2 | X7: =TEXT(WEEKDAY(E7,2),"0")&" - "&TEXT(E7,"dddd") -> 6 - Saturday | Y7: =_xlfn.IFS(C7<18,"Child (0-17)",C7<40,"Young Adult (18-39)",C7<60,"Adult (40-59)",TRUE(),"Senior (60+)") -> Young Adult (18-39) | Z7: =ROUND(G7-E7,0) -> 1 | AA7: =L7+M7 -> 128 | AB7: =IFERROR(ROUND(Q7/AA7,2),0) -> 32.52 | AC7: =IF(AND(K7="Critical",N7="No"),"URGENT - No Bed","Normal") -> Normal | AD7: =INDEX(Lookup_Tables!$B$3:$B$12,MATCH(H7,Lookup_Tables!$A$3:$A$12,0)) -> 4400000 | AE7: =INDEX(Lookup_Tables!$C$3:$C$12,MATCH(H7,Lookup_Tables!$A$3:$A$12,0)) -> Dr. Neha Chopra | AF7: =IFERROR(INDEX(Lookup_Tables!$F$16:$F$45,MATCH(I7,Lookup_Tables!$E$16:$E$45,0)),"N/A") -> EMP218 | AG7: =_xlfn.IFS(R7="Recovered",4,R7="Referred",3,R7="Admitted",2,R7="Deceased",1,TRUE(),0) -> 4 | AH7: =IF(T7>=4,"Satisfied",IF(T7>=3,"Neutral","Needs Improvement")) -> Satisfied
A8: PT10007 | B8: Meera Rao | C8: 46 | D8: Male | E8: 45582 | F8: 02:05 | G8: 45587 | H8: ENT | I8: Dr. Riya Singh | J8: Ear Infection | K8: High | L8: 35 | M8: 115 | N8: Yes | O8: Private | P8: Insurance Claim | Q8: 9153.73 | R8: Referred | S8: Chennai | T8: 1 | U8: =YEAR(E8) -> 2024 | V8: =TEXT(E8,"MMM-YYYY") -> Oct-2024 | W8: =MONTH(E8) -> 10 | X8: =TEXT(WEEKDAY(E8,2),"0")&" - "&TEXT(E8,"dddd") -> 4 - Thursday | Y8: =_xlfn.IFS(C8<18,"Child (0-17)",C8<40,"Young Adult (18-39)",C8<60,"Adult (40-59)",TRUE(),"Senior (60+)") -> Adult (40-59) | Z8: =ROUND(G8-E8,0) -> 5 | AA8: =L8+M8 -> 150 | AB8: =IFERROR(ROUND(Q8/AA8,2),0) -> 61.02 | AC8: =IF(AND(K8="Critical",N8="No"),"URGENT - No Bed","Normal") -> Normal | AD8: =INDEX(Lookup_Tables!$B$3:$B$12,MATCH(H8,Lookup_Tables!$A$3:$A$12,0)) -> 2200000 | AE8: =INDEX(Lookup_Tables!$C$3:$C$12,MATCH(H8,Lookup_Tables!$A$3:$A$12,0)) -> Dr. Rohan Das | AF8: =IFERROR(INDEX(Lookup_Tables!$F$16:$F$45,MATCH(I8,Lookup_Tables!$E$16:$E$45,0)),"N/A") -> EMP205 | AG8: =_xlfn.IFS(R8="Recovered",4,R8="Referred",3,R8="Admitted",2,R8="Deceased",1,TRUE(),0) -> 3 | AH8: =IF(T8>=4,"Satisfied",IF(T8>=3,"Neutral","Needs Improvement")) -> Needs Improvement
A9: PT10008 | B9: Sameer Iyer | C9: 7 | D9: Male | E9: 45635 | F9: 20:25 | G9: 45639 | H9: ENT | I9: Dr. Riya Singh | J9: Ear Infection | K9: High | L9: 19 | M9: 53 | N9: Yes | O9: Private | P9: Card | Q9: 7471.88 | R9: Recovered | S9: Delhi | T9: 3 | U9: =YEAR(E9) -> 2024 | V9: =TEXT(E9,"MMM-YYYY") -> Dec-2024 | W9: =MONTH(E9) -> 12 | X9: =TEXT(WEEKDAY(E9,2),"0")&" - "&TEXT(E9,"dddd") -> 1 - Monday | Y9: =_xlfn.IFS(C9<18,"Child (0-17)",C9<40,"Young Adult (18-39)",C9<60,"Adult (40-59)",TRUE(),"Senior (60+)") -> Child (0-17) | Z9: =ROUND(G9-E9,0) -> 4 | AA9: =L9+M9 -> 72 | AB9: =IFERROR(ROUND(Q9/AA9,2),0) -> 103.78 | AC9: =IF(AND(K9="Critical",N9="No"),"URGENT - No Bed","Normal") -> Normal | AD9: =INDEX(Lookup_Tables!$B$3:$B$12,MATCH(H9,Lookup_Tables!$A$3:$A$12,0)) -> 2200000 | AE9: =INDEX(Lookup_Tables!$C$3:$C$12,MATCH(H9,Lookup_Tables!$A$3:$A$12,0)) -> Dr. Rohan Das | AF9: =IFERROR(INDEX(Lookup_Tables!$F$16:$F$45,MATCH(I9,Lookup_Tables!$E$16:$E$45,0)),"N/A") -> EMP205 | AG9: =_xlfn.IFS(R9="Recovered",4,R9="Referred",3,R9="Admitted",2,R9="Deceased",1,TRUE(),0) -> 4 | AH9: =IF(T9>=4,"Satisfied",IF(T9>=3,"Neutral","Needs Improvement")) -> Neutral
A10: PT10009 | B10: Myra Gupta | C10: 21 | D10: Female | E10: 45461 | F10: 02:40 | G10: 45462 | H10: Pediatrics | I10: Dr. Sai Reddy | J10: Allergic Reaction | K10: Low | L10: 36 | M10: 38 | N10: No | O10: Private | P10: Insurance Claim | Q10: 1355.99 | R10: Recovered | S10: Pune | T10: 4 | U10: =YEAR(E10) -> 2024 | V10: =TEXT(E10,"MMM-YYYY") -> Jun-2024 | W10: =MONTH(E10) -> 6 | X10: =TEXT(WEEKDAY(E10,2),"0")&" - "&TEXT(E10,"dddd") -> 2 - Tuesday | Y10: =_xlfn.IFS(C10<18,"Child (0-17)",C10<40,"Young Adult (18-39)",C10<60,"Adult (40-59)",TRUE(),"Senior (60+)") -> Young Adult (18-39) | Z10: =ROUND(G10-E10,0) -> 1 | AA10: =L10+M10 -> 74 | AB10: =IFERROR(ROUND(Q10/AA10,2),0) -> 18.32 | AC10: =IF(AND(K10="Critical",N10="No"),"URGENT - No Bed","Normal") -> Normal | AD10: =INDEX(Lookup_Tables!$B$3:$B$12,MATCH(H10,Lookup_Tables!$A$3:$A$12,0)) -> 3100000 | AE10: =INDEX(Lookup_Tables!$C$3:$C$12,MATCH(H10,Lookup_Tables!$A$3:$A$12,0)) -> Dr. Kavita Rao | AF10: =IFERROR(INDEX(Lookup_Tables!$F$16:$F$45,MATCH(I10,Lookup_Tables!$E$16:$E$45,0)),"N/A") -> EMP226 | AG10: =_xlfn.IFS(R10="Recovered",4,R10="Referred",3,R10="Admitted",2,R10="Deceased",1,TRUE(),0) -> 4 | AH10: =IF(T10>=4,"Satisfied",IF(T10>=3,"Neutral","Needs Improvement")) -> Satisfied
A11: PT10010 | B11: Isha Kumar | C11: 23 | D11: Male | E11: 45512 | F11: 11:30 | G11: 45512 | H11: Gynecology | I11: Dr. Deepak Mehta | J11: Labor Complication | K11: Medium | L11: 18 | M11: 55 | N11: No | O11: Corporate | P11: Cash | Q11: 3322.31 | R11: Recovered | S11: Ahmedabad | T11: 3 | U11: =YEAR(E11) -> 2024 | V11: =TEXT(E11,"MMM-YYYY") -> Aug-2024 | W11: =MONTH(E11) -> 8 | X11: =TEXT(WEEKDAY(E11,2),"0")&" - "&TEXT(E11,"dddd") -> 4 - Thursday | Y11: =_xlfn.IFS(C11<18,"Child (0-17)",C11<40,"Young Adult (18-39)",C11<60,"Adult (40-59)",TRUE(),"Senior (60+)") -> Young Adult (18-39) | Z11: =ROUND(G11-E11,0) -> 0 | AA11: =L11+M11 -> 73 | AB11: =IFERROR(ROUND(Q11/AA11,2),0) -> 45.51 | AC11: =IF(AND(K11="Critical",N11="No"),"URGENT - No Bed","Normal") -> Normal | AD11: =INDEX(Lookup_Tables!$B$3:$B$12,MATCH(H11,Lookup_Tables!$A$3:$A$12,0)) -> 3000000 | AE11: =INDEX(Lookup_Tables!$C$3:$C$12,MATCH(H11,Lookup_Tables!$A$3:$A$12,0)) -> Dr. Pooja Iyer | AF11: =IFERROR(INDEX(Lookup_Tables!$F$16:$F$45,MATCH(I11,Lookup_Tables!$E$16:$E$45,0)),"N/A") -> EMP214 | AG11: =_xlfn.IFS(R11="Recovered",4,R11="Referred",3,R11="Admitted",2,R11="Deceased",1,TRUE(),0) -> 4 | AH11: =IF(T11>=4,"Satisfied",IF(T11>=3,"Neutral","Needs Improvement")) -> Neutral
A12: PT10011 | B12: Ishaan Chopra | C12: 71 | D12: Male | E12: 45528 | F12: 07:05 | G12: 45533 | H12: ENT | I12: Dr. Riya Singh | J12: Sinusitis | K12: High | L12: 39 | M12: 46 | N12: No | O12: None | P12: Card | Q12: 6522.62 | R12: Recovered | S12: Chennai | T12: 4 | U12: =YEAR(E12) -> 2024 | V12: =TEXT(E12,"MMM-YYYY") -> Aug-2024 | W12: =MONTH(E12) -> 8 | X12: =TEXT(WEEKDAY(E12,2),"0")&" - "&TEXT(E12,"dddd") -> 6 - Saturday | Y12: =_xlfn.IFS(C12<18,"Child (0-17)",C12<40,"Young Adult (18-39)",C12<60,"Adult (40-59)",TRUE(),"Senior (60+)") -> Senior (60+) | Z12: =ROUND(G12-E12,0) -> 5 | AA12: =L12+M12 -> 85 | AB12: =IFERROR(ROUND(Q12/AA12,2),0) -> 76.74 | AC12: =IF(AND(K12="Critical",N12="No"),"URGENT - No Bed","Normal") -> Normal | AD12: =INDEX(Lookup_Tables!$B$3:$B$12,MATCH(H12,Lookup_Tables!$A$3:$A$12,0)) -> 2200000 | AE12: =INDEX(Lookup_Tables!$C$3:$C$12,MATCH(H12,Lookup_Tables!$A$3:$A$12,0)) -> Dr. Rohan Das | AF12: =IFERROR(INDEX(Lookup_Tables!$F$16:$F$45,MATCH(I12,Lookup_Tables!$E$16:$E$45,0)),"N/A") -> EMP205 | AG12: =_xlfn.IFS(R12="Recovered",4,R12="Referred",3,R12="Admitted",2,R12="Deceased",1,TRUE(),0) -> 4 | AH12: =IF(T12>=4,"Satisfied",IF(T12>=3,"Neutral","Needs Improvement")) -> Satisfied
A13: PT10012 | B13: Sanjay Chauhan | C13: 43 | D13: Male | E13: 45486 | F13: 00:30 | G13: 45500 | H13: General Medicine | I13: Dr. Sameer Khan | J13: Diabetes Complication | K13: Critical | L13: 13 | M13: 238 | N13: Yes | O13: None | P13: Insurance Claim | Q13: 18379.59 | R13: Recovered | S13: Delhi | T13: 3 | U13: =YEAR(E13) -> 2024 | V13: =TEXT(E13,"MMM-YYYY") -> Jul-2024 | W13: =MONTH(E13) -> 7 | X13: =TEXT(WEEKDAY(E13,2),"0")&" - "&TEXT(E13,"dddd") -> 6 - Saturday | Y13: =_xlfn.IFS(C13<18,"Child (0-17)",C13<40,"Young Adult (18-39)",C13<60,"Adult (40-59)",TRUE(),"Senior (60+)") -> Adult (40-59) | Z13: =ROUND(G13-E13,0) -> 14 | AA13: =L13+M13 -> 251 | AB13: =IFERROR(ROUND(Q13/AA13,2),0) -> 73.23 | AC13: =IF(AND(K13="Critical",N13="No"),"URGENT - No Bed","Normal") -> Normal | AD13: =INDEX(Lookup_Tables!$B$3:$B$12,MATCH(H13,Lookup_Tables!$A$3:$A$12,0)) -> 2800000 | AE13: =INDEX(Lookup_Tables!$C$3:$C$12,MATCH(H13,Lookup_Tables!$A$3:$A$12,0)) -> Dr. Suresh Nair | AF13: =IFERROR(INDEX(Lookup_Tables!$F$16:$F$45,MATCH(I13,Lookup_Tables!$E$16:$E$45,0)),"N/A") -> EMP211 | AG13: =_xlfn.IFS(R13="Recovered",4,R13="Referred",3,R13="Admitted",2,R13="Deceased",1,TRUE(),0) -> 4 | AH13: =IF(T13>=4,"Satisfied",IF(T13>=3,"Neutral","Needs Improvement")) -> Neutral
... A5001: PT15000 | B5001: Deepak Pillai | C5001: 51 | D5001: Female | E5001: 45538 | F5001: 01:40 | G5001: 45538 | H5001: Pediatrics | I5001: Dr. Nisha Sharma | J5001: Vomiting | K5001: Low | L5001: 90 | M5001: 45 | N5001: No | O5001: Private | P5001: Card | Q5001: 2332.85 | R5001: Recovered | S5001: Delhi | T5001: 5 | U5001: =YEAR(E5001) -> 2024 | V5001: =TEXT(E5001,"MMM-YYYY") -> Sep-2024 | W5001: =MONTH(E5001) -> 9 | X5001: =TEXT(WEEKDAY(E5001,2),"0")&" - "&TEXT(E5001,"dddd") -> 2 - Tuesday | Y5001: =_xlfn.IFS(C5001<18,"Child (0-17)",C5001<40,"Young Adult (18-39)",C5001<60,"Adult (40-59)",TRUE(),"Senior (60+)") -> Adult (40-59) | Z5001: =ROUND(G5001-E5001,0) -> 0 | AA5001: =L5001+M5001 -> 135 | AB5001: =IFERROR(ROUND(Q5001/AA5001,2),0) -> 17.28 | AC5001: =IF(AND(K5001="Critical",N5001="No"),"URGENT - No Bed","Normal") -> Normal | AD5001: =INDEX(Lookup_Tables!$B$3:$B$12,MATCH(H5001,Lookup_Tables!$A$3:$A$12,0)) -> 3100000 | AE5001: =INDEX(Lookup_Tables!$C$3:$C$12,MATCH(H5001,Lookup_Tables!$A$3:$A$12,0)) -> Dr. Kavita Rao | AF5001: =IFERROR(INDEX(Lookup_Tables!$F$16:$F$45,MATCH(I5001,Lookup_Tables!$E$16:$E$45,0)),"N/A") -> EMP225 | AG5001: =_xlfn.IFS(R5001="Recovered",4,R5001="Referred",3,R5001="Admitted",2,R5001="Deceased",1,TRUE(),0) -> 4 | AH5001: =IF(T5001>=4,"Satisfied",IF(T5001>=3,"Neutral","Needs Improvement")) -> Satisfied

Sheet Lookup_Tables
A1: Department Reference
A2: Department | B2: Annual Budget (INR) | C2: Department Head
A3: Cardiology | B3: 4200000 | C3: Dr. Anil Kapoor
A4: Neurology | B4: 3900000 | C4: Dr. Rina Mehta
A5: Orthopedics | B5: 3600000 | C5: Dr. Sameer Joshi
A6: Pediatrics | B6: 3100000 | C6: Dr. Kavita Rao
A7: General Medicine | B7: 2800000 | C7: Dr. Suresh Nair
A8: Emergency Trauma | B8: 4600000 | C8: Dr. Farhan Khan
A9: Gynecology | B9: 3000000 | C9: Dr. Pooja Iyer
A10: ENT | B10: 2200000 | C10: Dr. Rohan Das
A11: Oncology | B11: 4400000 | C11: Dr. Neha Chopra
A12: Urology | B12: 2700000 | C12: Dr. Vikram Singh
A14: Doctor Reference
E15: Doctor Name | F15: Employee ID | G15: Department | H15: Years Experience
E16: Dr. Mohammed Kumar | F16: EMP200 | G16: Cardiology | H16: 23
E17: Dr. Riya Rao | F17: EMP201 | G17: Cardiology | H17: 16
E18: Dr. Vivaan Das | F18: EMP202 | G18: Cardiology | H18: 17
E19: Dr. Aadhya Bose | F19: EMP203 | G19: ENT | H19: 22
E20: Dr. Amit Kumar | F20: EMP204 | G20: ENT | H20: 15
E21: Dr. Riya Singh | F21: EMP205 | G21: ENT | H21: 19
E22: Dr. Manoj Rao | F22: EMP206 | G22: Emergency Trauma | H22: 21
E23: Dr. Ravi Menon | F23: EMP207 | G23: Emergency Trauma | H23: 7
E24: Dr. Riya Chatterjee | F24: EMP208 | G24: Emergency Trauma | H24: 3
E25: Dr. Anita Reddy | F25: EMP209 | G25: General Medicine | H25: 8
E26: Dr. Ayesha Bhat | F26: EMP210 | G26: General Medicine | H26: 8
E27: Dr. Sameer Khan | F27: EMP211 | G27: General Medicine | H27: 22
... E45: Dr. Sara Chatterjee | F45: EMP229 | G45: Urology | H45: 13

Sheet Pivot_Summary
A2: 1. Patients by Department
A3: Department | B3: Patient Count | C3: % of Total
A4: Cardiology | B4: =COUNTIF(Cleaned_Data!$H$2:$H$5001,A4) -> 484 | C4: =ROUND(B4/SUM($B$4:$B$13),3) -> 0.097
A5: Neurology | B5: =COUNTIF(Cleaned_Data!$H$2:$H$5001,A5) -> 490 | C5: =ROUND(B5/SUM($B$4:$B$13),3) -> 0.098
A6: Orthopedics | B6: =COUNTIF(Cleaned_Data!$H$2:$H$5001,A6) -> 488 | C6: =ROUND(B6/SUM($B$4:$B$13),3) -> 0.098
A7: Pediatrics | B7: =COUNTIF(Cleaned_Data!$H$2:$H$5001,A7) -> 498 | C7: =ROUND(B7/SUM($B$4:$B$13),3) -> 0.1
A8: General Medicine | B8: =COUNTIF(Cleaned_Data!$H$2:$H$5001,A8) -> 522 | C8: =ROUND(B8/SUM($B$4:$B$13),3) -> 0.104
A9: Emergency Trauma | B9: =COUNTIF(Cleaned_Data!$H$2:$H$5001,A9) -> 514 | C9: =ROUND(B9/SUM($B$4:$B$13),3) -> 0.103
A10: Gynecology | B10: =COUNTIF(Cleaned_Data!$H$2:$H$5001,A10) -> 517 | C10: =ROUND(B10/SUM($B$4:$B$13),3) -> 0.103
A11: ENT | B11: =COUNTIF(Cleaned_Data!$H$2:$H$5001,A11) -> 502 | C11: =ROUND(B11/SUM($B$4:$B$13),3) -> 0.1
A12: Oncology | B12: =COUNTIF(Cleaned_Data!$H$2:$H$5001,A12) -> 514 | C12: =ROUND(B12/SUM($B$4:$B$13),3) -> 0.103
A13: Urology | B13: =COUNTIF(Cleaned_Data!$H$2:$H$5001,A13) -> 471 | C13: =ROUND(B13/SUM($B$4:$B$13),3) -> 0.094
A15: 2. Patients by Severity Level
A16: Severity Level | B16: Patient Count | C16: % of Total
A17: Low | B17: =COUNTIF(Cleaned_Data!$K$2:$K$5001,A17) -> 1757 | C17: =ROUND(B17/SUM($B$17:$B$20),3) -> 0.351
A18: Medium | B18: =COUNTIF(Cleaned_Data!$K$2:$K$5001,A18) -> 1727 | C18: =ROUND(B18/SUM($B$17:$B$20),3) -> 0.345
A19: High | B19: =COUNTIF(Cleaned_Data!$K$2:$K$5001,A19) -> 1113 | C19: =ROUND(B19/SUM($B$17:$B$20),3) -> 0.223
A20: Critical | B20: =COUNTIF(Cleaned_Data!$K$2:$K$5001,A20) -> 403 | C20: =ROUND(B20/SUM($B$17:$B$20),3) -> 0.081
A22: 3. Average Waiting Time by Department (Minutes)
A23: Department | B23: Avg Waiting Time
A24: Cardiology | B24: =ROUND(AVERAGEIFS(Cleaned_Data!$L$2:$L$5001,Cleaned_Data!$H$2:$H$5001,A24),1) -> 40.4
A25: Neurology | B25: =ROUND(AVERAGEIFS(Cleaned_Data!$L$2:$L$5001,Cleaned_Data!$H$2:$H$5001,A25),1) -> 41.1
A26: Orthopedics | B26: =ROUND(AVERAGEIFS(Cleaned_Data!$L$2:$L$5001,Cleaned_Data!$H$2:$H$5001,A26),1) -> 40.9
A27: Pediatrics | B27: =ROUND(AVERAGEIFS(Cleaned_Data!$L$2:$L$5001,Cleaned_Data!$H$2:$H$5001,A27),1) -> 41
A28: General Medicine | B28: =ROUND(AVERAGEIFS(Cleaned_Data!$L$2:$L$5001,Cleaned_Data!$H$2:$H$5001,A28),1) -> 42.8
A29: Emergency Trauma | B29: =ROUND(AVERAGEIFS(Cleaned_Data!$L$2:$L$5001,Cleaned_Data!$H$2:$H$5001,A29),1) -> 41.9
A30: Gynecology | B30: =ROUND(AVERAGEIFS(Cleaned_Data!$L$2:$L$5001,Cleaned_Data!$H$2:$H$5001,A30),1) -> 41.2
A31: ENT | B31: =ROUND(AVERAGEIFS(Cleaned_Data!$L$2:$L$5001,Cleaned_Data!$H$2:$H$5001,A31),1) -> 40.5
A32: Oncology | B32: =ROUND(AVERAGEIFS(Cleaned_Data!$L$2:$L$5001,Cleaned_Data!$H$2:$H$5001,A32),1) -> 39.4
A33: Urology | B33: =ROUND(AVERAGEIFS(Cleaned_Data!$L$2:$L$5001,Cleaned_Data!$H$2:$H$5001,A33),1) -> 37.8
A35: 4. Monthly Patient Trend (2024)
A36: Month | B36: Patient Count
A37: Jan | B37: =COUNTIFS(Cleaned_Data!$W$2:$W$5001,1,Cleaned_Data!$U$2:$U$5001,2024) -> 417
A38: Feb | B38: =COUNTIFS(Cleaned_Data!$W$2:$W$5001,2,Cleaned_Data!$U$2:$U$5001,2024) -> 381
A39: Mar | B39: =COUNTIFS(Cleaned_Data!$W$2:$W$5001,3,Cleaned_Data!$U$2:$U$5001,2024) -> 430
A40: Apr | B40: =COUNTIFS(Cleaned_Data!$W$2:$W$5001,4,Cleaned_Data!$U$2:$U$5001,2024) -> 419
A41: May | B41: =COUNTIFS(Cleaned_Data!$W$2:$W$5001,5,Cleaned_Data!$U$2:$U$5001,2024) -> 419
A42: Jun | B42: =COUNTIFS(Cleaned_Data!$W$2:$W$5001,6,Cleaned_Data!$U$2:$U$5001,2024) -> 427
A43: Jul | B43: =COUNTIFS(Cleaned_Data!$W$2:$W$5001,7,Cleaned_Data!$U$2:$U$5001,2024) -> 413
A44: Aug | B44: =COUNTIFS(Cleaned_Data!$W$2:$W$5001,8,Cleaned_Data!$U$2:$U$5001,2024) -> 415
A45: Sep | B45: =COUNTIFS(Cleaned_Data!$W$2:$W$5001,9,Cleaned_Data!$U$2:$U$5001,2024) -> 399
A46: Oct | B46: =COUNTIFS(Cleaned_Data!$W$2:$W$5001,10,Cleaned_Data!$U$2:$U$5001,2024) -> 439
A47: Nov | B47: =COUNTIFS(Cleaned_Data!$W$2:$W$5001,11,Cleaned_Data!$U$2:$U$5001,2024) -> 423
A48: Dec | B48: =COUNTIFS(Cleaned_Data!$W$2:$W$5001,12,Cleaned_Data!$U$2:$U$5001,2024) -> 418
A50: 5. Doctor-wise Patient Count
A51: Doctor Name | B51: Patient Count
A52: Dr. Mohammed Kumar | B52: =COUNTIF(Cleaned_Data!$I$2:$I$5001,A52) -> 152
A53: Dr. Riya Rao | B53: =COUNTIF(Cleaned_Data!$I$2:$I$5001,A53) -> 173
A54: Dr. Vivaan Das | B54: =COUNTIF(Cleaned_Data!$I$2:$I$5001,A54) -> 159
A55: Dr. Aadhya Bose | B55: =COUNTIF(Cleaned_Data!$I$2:$I$5001,A55) -> 167
A56: Dr. Amit Kumar | B56: =COUNTIF(Cleaned_Data!$I$2:$I$5001,A56) -> 157
A57: Dr. Riya Singh | B57: =COUNTIF(Cleaned_Data!$I$2:$I$5001,A57) -> 178
A58: Dr. Manoj Rao | B58: =COUNTIF(Cleaned_Data!$I$2:$I$5001,A58) -> 150
A59: Dr. Ravi Menon | B59: =COUNTIF(Cleaned_Data!$I$2:$I$5001,A59) -> 193
A60: Dr. Riya Chatterjee | B60: =COUNTIF(Cleaned_Data!$I$2:$I$5001,A60) -> 171
A61: Dr. Anita Reddy | B61: =COUNTIF(Cleaned_Data!$I$2:$I$5001,A61) -> 189
A62: Dr. Ayesha Bhat | B62: =COUNTIF(Cleaned_Data!$I$2:$I$5001,A62) -> 179
A63: Dr. Sameer Khan | B63: =COUNTIF(Cleaned_Data!$I$2:$I$5001,A63) -> 154
... A81: Dr. Sara Chatterjee | B81: =COUNTIF(Cleaned_Data!$I$2:$I$5001,A81) -> 150
A83: 6. Gender Distribution
A84: Gender | B84: Patient Count | C84: % of Total
A85: Male | B85: =COUNTIF(Cleaned_Data!$D$2:$D$5001,A85) -> 2385 | C85: =ROUND(B85/SUM($B$85:$B$87),3) -> 0.477
A86: Female | B86: =COUNTIF(Cleaned_Data!$D$2:$D$5001,A86) -> 2536 | C86: =ROUND(B86/SUM($B$85:$B$87),3) -> 0.507
A87: Other | B87: =COUNTIF(Cleaned_Data!$D$2:$D$5001,A87) -> 79 | C87: =ROUND(B87/SUM($B$85:$B$87),3) -> 0.016
A89: 7. Age Group Analysis
A90: Age Group | B90: Patient Count | C90: Average Age
A91: Child (0-17) | B91: =COUNTIF(Cleaned_Data!$Y$2:$Y$5001,A91) -> 566 | C91: =IFERROR(ROUND(AVERAGEIFS(Cleaned_Data!$C$2:$C$5001,Cleaned_Data!$Y$2:$Y$5001,A91),1),0) -> 8.6
A92: Young Adult (18-39) | B92: =COUNTIF(Cleaned_Data!$Y$2:$Y$5001,A92) -> 1735 | C92: =IFERROR(ROUND(AVERAGEIFS(Cleaned_Data!$C$2:$C$5001,Cleaned_Data!$Y$2:$Y$5001,A92),1),0) -> 29.7
A93: Adult (40-59) | B93: =COUNTIF(Cleaned_Data!$Y$2:$Y$5001,A93) -> 1787 | C93: =IFERROR(ROUND(AVERAGEIFS(Cleaned_Data!$C$2:$C$5001,Cleaned_Data!$Y$2:$Y$5001,A93),1),0) -> 48.7
A94: Senior (60+) | B94: =COUNTIF(Cleaned_Data!$Y$2:$Y$5001,A94) -> 912 | C94: =IFERROR(ROUND(AVERAGEIFS(Cleaned_Data!$C$2:$C$5001,Cleaned_Data!$Y$2:$Y$5001,A94),1),0) -> 70.5
A96: 8. Revenue by Department (INR)
A97: Department | B97: Total Revenue
A98: Cardiology | B98: =ROUND(SUMIFS(Cleaned_Data!$Q$2:$Q$5001,Cleaned_Data!$H$2:$H$5001,A98),0) -> 2561379
A99: Neurology | B99: =ROUND(SUMIFS(Cleaned_Data!$Q$2:$Q$5001,Cleaned_Data!$H$2:$H$5001,A99),0) -> 2563578
A100: Orthopedics | B100: =ROUND(SUMIFS(Cleaned_Data!$Q$2:$Q$5001,Cleaned_Data!$H$2:$H$5001,A100),0) -> 2439535
A101: Pediatrics | B101: =ROUND(SUMIFS(Cleaned_Data!$Q$2:$Q$5001,Cleaned_Data!$H$2:$H$5001,A101),0) -> 2568366
A102: General Medicine | B102: =ROUND(SUMIFS(Cleaned_Data!$Q$2:$Q$5001,Cleaned_Data!$H$2:$H$5001,A102),0) -> 2534156
A103: Emergency Trauma | B103: =ROUND(SUMIFS(Cleaned_Data!$Q$2:$Q$5001,Cleaned_Data!$H$2:$H$5001,A103),0) -> 2632411
A104: Gynecology | B104: =ROUND(SUMIFS(Cleaned_Data!$Q$2:$Q$5001,Cleaned_Data!$H$2:$H$5001,A104),0) -> 2574511
A105: ENT | B105: =ROUND(SUMIFS(Cleaned_Data!$Q$2:$Q$5001,Cleaned_Data!$H$2:$H$5001,A105),0) -> 2575437
A106: Oncology | B106: =ROUND(SUMIFS(Cleaned_Data!$Q$2:$Q$5001,Cleaned_Data!$H$2:$H$5001,A106),0) -> 2712956
A107: Urology | B107: =ROUND(SUMIFS(Cleaned_Data!$Q$2:$Q$5001,Cleaned_Data!$H$2:$H$5001,A107),0) -> 2647331
A109: 9. Patient Outcomes
A110: Outcome | B110: Patient Count | C110: % of Total
A111: Recovered | B111: =COUNTIF(Cleaned_Data!$R$2:$R$5001,A111) -> 3647 | C111: =ROUND(B111/SUM($B$111:$B$114),3) -> 0.729
A112: Admitted | B112: =COUNTIF(Cleaned_Data!$R$2:$R$5001,A112) -> 774 | C112: =ROUND(B112/SUM($B$111:$B$114),3) -> 0.155
A113: Referred | B113: =COUNTIF(Cleaned_Data!$R$2:$R$5001,A113) -> 461 | C113: =ROUND(B113/SUM($B$111:$B$114),3) -> 0.092
A114: Deceased | B114: =COUNTIF(Cleaned_Data!$R$2:$R$5001,A114) -> 118 | C114: =ROUND(B114/SUM($B$111:$B$114),3) -> 0.024
A116: 10. Satisfaction Score Analysis
A117: Score | B117: Patient Count | C117: % of Total
A118: 1 | B118: =COUNTIF(Cleaned_Data!$T$2:$T$5001,A118) -> 106 | C118: =IFERROR(ROUND(B118/SUM($B$118:$B$122),3),0) -> 0.021
A119: 2 | B119: =COUNTIF(Cleaned_Data!$T$2:$T$5001,A119) -> 545 | C119: =IFERROR(ROUND(B119/SUM($B$118:$B$122),3),0) -> 0.109
A120: 3 | B120: =COUNTIF(Cleaned_Data!$T$2:$T$5001,A120) -> 1445 | C120: =IFERROR(ROUND(B120/SUM($B$118:$B$122),3),0) -> 0.289
A121: 4 | B121: =COUNTIF(Cleaned_Data!$T$2:$T$5001,A121) -> 1689 | C121: =IFERROR(ROUND(B121/SUM($B$118:$B$122),3),0) -> 0.338
A122: 5 | B122: =COUNTIF(Cleaned_Data!$T$2:$T$5001,A122) -> 1215 | C122: =IFERROR(ROUND(B122/SUM($B$118:$B$122),3),0) -> 0.243
A125: 11. Age Distribution (10-Year Bins)
A126: Age Bin | B126: Patient Count
A127: 0-9 | B127: =COUNTIFS(Cleaned_Data!$C$2:$C$5001,">="&0,Cleaned_Data!$C$2:$C$5001,"<="&9) -> 275
A128: 10-19 | B128: =COUNTIFS(Cleaned_Data!$C$2:$C$5001,">="&10,Cleaned_Data!$C$2:$C$5001,"<="&19) -> 391
A129: 20-29 | B129: =COUNTIFS(Cleaned_Data!$C$2:$C$5001,">="&20,Cleaned_Data!$C$2:$C$5001,"<="&29) -> 715
...
